LICENSE
MANIFEST.in
README.md
README.rst
setup.cfg
setup.py
nanocomp/NanoComp.py
nanocomp/__init__.py
nanocomp/compplots.py
nanocomp/utils.py
nanocomp/version.py
nanocomp.egg-info/PKG-INFO
nanocomp.egg-info/SOURCES.txt
nanocomp.egg-info/dependency_links.txt
nanocomp.egg-info/entry_points.txt
nanocomp.egg-info/requires.txt
nanocomp.egg-info/top_level.txt
scripts/end_reason_comparison.py
scripts/get_cumulative_yield_table.py
scripts/length_plots_only.py
scripts/poor_state.py
scripts/test.sh