Metadata-Version: 2.1
Name: nanocomp
Version: 1.25.5
Summary: Comparing runs of Oxford Nanopore sequencing data and alignments
Home-page: https://github.com/wdecoster/NanoComp
Author: Wouter De Coster
Author-email: decosterwouter@gmail.com
License: MIT
Keywords: nanopore sequencing plotting quality control
Classifier: Development Status :: 4 - Beta
Classifier: Intended Audience :: Science/Research
Classifier: Topic :: Scientific/Engineering :: Bio-Informatics
Classifier: License :: OSI Approved :: MIT License
Classifier: Programming Language :: Python :: 3
Classifier: Programming Language :: Python :: 3.3
Classifier: Programming Language :: Python :: 3.4
Classifier: Programming Language :: Python :: 3.5
Requires-Python: >=3
License-File: LICENSE
